cirq_rigetti/__init__.py
cirq_rigetti/_version.py
cirq_rigetti/_version_test.py
cirq_rigetti/aspen_device.py
cirq_rigetti/aspen_device_test.py
cirq_rigetti/circuit_sweep_executors.py
cirq_rigetti/circuit_sweep_executors_test.py
cirq_rigetti/circuit_transformers.py
cirq_rigetti/circuit_transformers_test.py
cirq_rigetti/conftest.py
cirq_rigetti/deprecation.py
cirq_rigetti/json_resolver_cache.py
cirq_rigetti/logging.py
cirq_rigetti/qcs_sampler_and_service_test.py
cirq_rigetti/quil_input.py
cirq_rigetti/quil_input_test.py
cirq_rigetti/quil_output.py
cirq_rigetti/quil_output_test.py
cirq_rigetti/sampler.py
cirq_rigetti/sampler_bell_circuit_test.py
cirq_rigetti/sampler_parametric_circuit_test.py
cirq_rigetti/sampler_readout_reassigned_qubits_test.py
cirq_rigetti/sampler_readout_separate_memory_regions_test.py
cirq_rigetti/sampler_test.py
cirq_rigetti/service.py
cirq_rigetti/service_bell_circuit_test.py
cirq_rigetti/service_parametric_circuit_test.py
cirq_rigetti/service_test.py
cirq_rigetti/json_test_data/AspenQubit.json
cirq_rigetti/json_test_data/AspenQubit.repr
cirq_rigetti/json_test_data/OctagonalQubit.json
cirq_rigetti/json_test_data/OctagonalQubit.repr
cirq_rigetti/json_test_data/RigettiQCSAspenDevice.json
cirq_rigetti/json_test_data/RigettiQCSAspenDevice.repr
cirq_rigetti/json_test_data/__init__.py
cirq_rigetti/json_test_data/spec.py
cirq_rigetti-1.5.0.dist-info/LICENSE
cirq_rigetti-1.5.0.dist-info/METADATA
cirq_rigetti-1.5.0.dist-info/WHEEL
cirq_rigetti-1.5.0.dist-info/top_level.txt
cirq_rigetti-1.5.0.dist-info/RECORD
